aparavi_client/__init__.py
aparavi_client/aparavi.py
aparavi_client/client.py
aparavi_client/py.typed
aparavi_client/cli/__init__.py
aparavi_client/cli/main.py
aparavi_client/cli/commands/__init__.py
aparavi_client/cli/commands/base.py
aparavi_client/cli/commands/events.py
aparavi_client/cli/commands/list.py
aparavi_client/cli/commands/start.py
aparavi_client/cli/commands/status.py
aparavi_client/cli/commands/stop.py
aparavi_client/cli/commands/store.py
aparavi_client/cli/commands/upload.py
aparavi_client/cli/monitors/__init__.py
aparavi_client/cli/monitors/base.py
aparavi_client/cli/monitors/events.py
aparavi_client/cli/monitors/generic.py
aparavi_client/cli/monitors/status.py
aparavi_client/cli/monitors/upload.py
aparavi_client/cli/ui/__init__.py
aparavi_client/cli/ui/box.py
aparavi_client/cli/ui/colors.py
aparavi_client/cli/ui/display.py
aparavi_client/cli/utils/__init__.py
aparavi_client/cli/utils/config.py
aparavi_client/cli/utils/file_utils.py
aparavi_client/cli/utils/formatters.py
aparavi_client/core/__init__.py
aparavi_client/core/constants.py
aparavi_client/core/dap_base.py
aparavi_client/core/dap_client.py
aparavi_client/core/exceptions.py
aparavi_client/core/transport.py
aparavi_client/core/transport_websocket.py
aparavi_client/mixins/chat.py
aparavi_client/mixins/connection.py
aparavi_client/mixins/data.py
aparavi_client/mixins/events.py
aparavi_client/mixins/execution.py
aparavi_client/mixins/ping.py
aparavi_client/mixins/store.py
aparavi_client/schema/__init__.py
aparavi_client/schema/doc.py
aparavi_client/schema/doc_filter.py
aparavi_client/schema/doc_group.py
aparavi_client/schema/doc_metadata.py
aparavi_client/schema/question.py
aparavi_client/types/__init__.py
aparavi_client/types/client.py
aparavi_client/types/data.py
aparavi_client/types/events.py
aparavi_client/types/pipeline.py
aparavi_client/types/task.py
aparavi_client_python-1.1.1.dist-info/LICENSE
aparavi_client_python-1.1.1.dist-info/METADATA
aparavi_client_python-1.1.1.dist-info/WHEEL
aparavi_client_python-1.1.1.dist-info/entry_points.txt
aparavi_client_python-1.1.1.dist-info/top_level.txt
aparavi_client_python-1.1.1.dist-info/RECORD
