Metadata-Version: 2.1
Name: aparavi-client-python
Version: 1.1.1
Summary: Aparavi Pipeline Python Client SDK
Author-email: Aparavi Development Team <dev@aparavi.com>
Maintainer-email: Aparavi Development Team <dev@aparavi.com>
License: MIT
Project-URL: Homepage, https://github.com/aparavi/aparavi-clients
Project-URL: Documentation, https://github.com/aparavi/aparavi-clients#readme
Project-URL: Repository, https://github.com/aparavi/aparavi-clients.git
Project-URL: Bug Reports, https://github.com/aparavi/aparavi-clients/issues
Keywords: aparavi,pipeline,dap,debug-adapter-protocol,data-processing,client-sdk,async,websocket
Classifier: Development Status :: 4 - Beta
Classifier: Intended Audience :: Developers
Classifier: Topic :: Software Development :: Libraries :: Python Modules
Classifier: Topic :: System :: Networking
Classifier: Topic :: Internet :: WWW/HTTP
Classifier: Programming Language :: Python :: 3
Classifier: Programming Language :: Python :: 3.8
Classifier: Programming Language :: Python :: 3.9
Classifier: Programming Language :: Python :: 3.10
Classifier: Programming Language :: Python :: 3.11
Classifier: Programming Language :: Python :: 3.12
Classifier: Operating System :: OS Independent
Classifier: Typing :: Typed
Requires-Python: >=3.8
License-File: LICENSE
Requires-Dist: websockets>=11.0.0
Requires-Dist: aiofiles>=23.0.0
Requires-Dist: pydantic>=2.0.0
Provides-Extra: dev
Requires-Dist: pytest>=7.0.0; extra == "dev"
Requires-Dist: pytest-asyncio>=0.21.0; extra == "dev"
Requires-Dist: black>=23.0.0; extra == "dev"
Requires-Dist: flake8>=6.0.0; extra == "dev"
Requires-Dist: mypy>=1.0.0; extra == "dev"
Requires-Dist: build>=0.10.0; extra == "dev"
Requires-Dist: twine>=4.0.0; extra == "dev"
Provides-Extra: test
Requires-Dist: pytest>=7.0.0; extra == "test"
Requires-Dist: pytest-asyncio>=0.21.0; extra == "test"
Requires-Dist: pytest-cov>=4.0.0; extra == "test"
